anomalyarmor_query_gateway/__init__.py
anomalyarmor_query_gateway/access_levels.py
anomalyarmor_query_gateway/audit.py
anomalyarmor_query_gateway/exceptions.py
anomalyarmor_query_gateway/gateway.py
anomalyarmor_query_gateway/parser.py
anomalyarmor_query_gateway/result.py
anomalyarmor_query_gateway/validator.py
anomalyarmor_query_gateway/dialects/__init__.py
anomalyarmor_query_gateway/dialects/base.py
anomalyarmor_query_gateway/dialects/clickhouse.py
anomalyarmor_query_gateway/dialects/databricks.py
anomalyarmor_query_gateway/dialects/mysql.py
anomalyarmor_query_gateway/dialects/postgres.py
anomalyarmor_query_gateway/dialects/sqlite.py
anomalyarmor_query_gateway-1.0.2.dist-info/METADATA
anomalyarmor_query_gateway-1.0.2.dist-info/WHEEL
anomalyarmor_query_gateway-1.0.2.dist-info/licenses/LICENSE
anomalyarmor_query_gateway-1.0.2.dist-info/RECORD
