Metadata-Version: 2.4
Name: anomalyarmor-query-gateway
Version: 1.0.2
Summary: SQL query security gateway for validating database access levels
Project-URL: Homepage, https://github.com/anomalyarmor/anomalyarmor-query-gateway
Project-URL: Documentation, https://github.com/anomalyarmor/anomalyarmor-query-gateway#readme
Project-URL: Repository, https://github.com/anomalyarmor/anomalyarmor-query-gateway
Project-URL: Issues, https://github.com/anomalyarmor/anomalyarmor-query-gateway/issues
Author-email: AnomalyArmor Team <security@anomalyarmor.com>
License: Apache-2.0
License-File: LICENSE
Keywords: access-control,audit,database,security,sql
Classifier: Development Status :: 5 - Production/Stable
Classifier: Intended Audience :: Developers
Classifier: License :: OSI Approved :: Apache Software License
Classifier: Programming Language :: Python :: 3.11
Classifier: Programming Language :: Python :: 3.12
Classifier: Topic :: Database
Classifier: Topic :: Security
Classifier: Typing :: Typed
Requires-Python: >=3.11
Requires-Dist: sqlglot>=26.0.0
Provides-Extra: dev
Requires-Dist: mypy>=1.8.0; extra == 'dev'
Requires-Dist: pytest-asyncio>=0.24.0; extra == 'dev'
Requires-Dist: pytest-cov>=4.0.0; extra == 'dev'
Requires-Dist: pytest>=8.0.0; extra == 'dev'
Requires-Dist: ruff>=0.8.0; extra == 'dev'
